huskarl/__init__.py
huskarl/core.py
huskarl/memory.py
huskarl/policy.py
huskarl/simulation.py
huskarl/agent/__init__.py
huskarl/agent/a2c.py
huskarl/agent/ddpg.py
huskarl/agent/dqn.py
huskarl-0.4.dist-info/METADATA
huskarl-0.4.dist-info/WHEEL
huskarl-0.4.dist-info/top_level.txt
huskarl-0.4.dist-info/RECORD
