Metadata-Version: 2.1
Name: huskarl
Version: 0.4
Summary: Deep Reinforcement Learning Framework
Home-page: https://github.com/danaugrs/huskarl
Author: Daniel Salvadori
Author-email: danaugrs@gmail.com
License: UNKNOWN
Platform: UNKNOWN
Classifier: Development Status :: 3 - Alpha
Classifier: Intended Audience :: Developers
Classifier: Topic :: Scientific/Engineering :: Artificial Intelligence
Classifier: License :: OSI Approved :: MIT License
Classifier: Programming Language :: Python :: 3
Requires-Python: >=3.6
Requires-Dist: cloudpickle
Requires-Dist: tensorflow (==2.0.0a0)
Requires-Dist: scipy
